celerabitpipelineintegration/__init__.py
celerabitpipelineintegration/__main__.py
celerabitpipelineintegration/int_main_module.py
celerabitpipelineintegration/model_credentials.py
celerabitpipelineintegration/model_execution_params.py
celerabitpipelineintegration/model_job.py
celerabitpipelineintegration/uc_authenticator.py
celerabitpipelineintegration/uc_scenario_runner.py
celerabitpipelineintegration/uc_scenario_status.py
celerabitpipelineintegration/util_compliance_evaluator.py
celerabitpipelineintegration/util_configuration.py
celerabitpipelineintegration/util_http.py
celerabitpipelineintegration/util_http_client.py
celerabitpipelineintegration/util_json.py
celerabitpipelineintegration/util_logger.py
celerabitpipelineintegration/util_misc.py
celerabitpipelineintegration/version.py
celerabit_pipeline_integration-2.0.13.dist-info/LICENCE
celerabit_pipeline_integration-2.0.13.dist-info/METADATA
celerabit_pipeline_integration-2.0.13.dist-info/WHEEL
celerabit_pipeline_integration-2.0.13.dist-info/top_level.txt
celerabit_pipeline_integration-2.0.13.dist-info/RECORD
