Metadata-Version: 2.1
Name: celerabit-pipeline-integration
Version: 2.0.13
Summary: Celerabit tools to integrate with pipelines
Home-page: https://git-codecommit.zone.amazonaws.com/v1/repos/celerabit-pipeline-integration-py-package
Author: Raul A. de Villa C.
Author-email: raul.devilla@techandsolve.com
Classifier: Programming Language :: Python :: 3
Classifier: Operating System :: OS Independent
Requires-Python: >=3.6
License-File: LICENCE
Requires-Dist: requests
Requires-Dist: urllib3
